qidicom/__init__.py
qidicom/hierarchy.py
qidicom/meta.py
qidicom/reader.py
qidicom/writer.py
qidicom-2.1.3.data/scripts/lsdicom
qidicom-2.1.3.dist-info/DESCRIPTION.rst
qidicom-2.1.3.dist-info/METADATA
qidicom-2.1.3.dist-info/metadata.json
qidicom-2.1.3.dist-info/RECORD
qidicom-2.1.3.dist-info/top_level.txt
qidicom-2.1.3.dist-info/WHEEL
