Metadata-Version: 2.0
Name: qidicom
Version: 2.1.3
Summary: DICOM facade.
Home-page: https://github.com/ohsu-qin/qidicom
Author: OHSU Knight Cancer Institute
Author-email: loneyf@ohsu.edu
License: MIT
Keywords: Imaging QIN DICOM
Platform: Any
Classifier: Development Status :: 5 - Production/Stable
Classifier: Topic :: Scientific/Engineering :: Bio-Informatics
Classifier: Environment :: Console
Classifier: Intended Audience :: Science/Research
Classifier: License :: OSI Approved :: MIT License
Classifier: Operating System :: OS Independent
Classifier: Programming Language :: Python
Classifier: Programming Language :: Python :: 2.6
Classifier: Programming Language :: Python :: 2.7
Requires-Dist: nose (==1.3.0)
Requires-Dist: pydicom (==0.9.8)
Requires-Dist: Sphinx (==1.2.2)
Requires-Dist: qiutil (==2.1.4)
